batss-1.0.2.dist-info/METADATA
batss-1.0.2.dist-info/WHEEL
batss-1.0.2.dist-info/licenses/LICENSE
batss/__init__.py
batss/batss_rust/.gitignore
batss/batss_rust/__init__.py
batss/batss_rust/batss_rust.cp312-win_amd64.pyd
batss/batss_rust/batss_rust.pyi
batss/crn.py
batss/py.typed
batss/simulation.py
batss/snapshot.py
batss-1.0.2.dist-info/RECORD
